[
  {
    "id": 1,
    "BankName": "DEUTSCHE BANK AG",
    "BankAddress": "TAUNUSANLAGE 12, 60254 FRANKFURT AM MAIN, GERMANY",
    "SwiftCode": "DEUTDEFF",
    "AccountName": "THEODY P. CAPARAS",
    "AccountAddress": "AVANTULO TOWERS I II III AND SOHO CENTRE CALLE 50,BANK DISTRICT - PANAMA CITY, PANAMA",
    "Types": "M0",
    "AuthorizedSignatory": "N/A",
    "AccountNumber": "458654789511",
    "Balance_1": "75000217899293",
    "Balance_2": "89,075,479,845,783,783.47",
    "Balance_3": "89,606,574,895,437.89",
    "mail": "pinguinofelice@yahoo.it",
    "reg_date": "2024-10-04 09:04:20",
    "TimeZone": "Europe/Berlin",
    "Note": "Current Account"
  },
  {
    "id": 2,
    "BankName": "DEUTSCHE BANK AG",
    "BankAddress": "TAUNUSANLAGE 12, 60254 FRANKFURT AM MAIN, GERMANY",
    "SwiftCode": "DEUTDEFFXXX",
    "AccountName": "AVANTULO S.A.",
    "AccountAddress": "SOHO CENTRE CALLE 50, AVANTULO TOWERS I II III, PANAMA CITY, N/A, N/A, PANAMA",
    "Types": "M1",
    "AuthorizedSignatory": "MR. FRANCIS ANTHONY JANKAUSKAS",
    "AccountNumber": "DE60500700100361982244",
    "Balance_1": "25,000,000,000,000.00",
    "Balance_2": "25,000,000,000,000.00",
    "Balance_3": "25,000,000,000,000.00",
    "mail": "pinguinofelice@yahoo.it",
    "reg_date": "2025-02-03 07:55:58",
    "TimeZone": "Europe/Berlin",
    "Note": "Current Account"
  },
  {
    "id": 3,
    "BankName": "DEUTSCHE BANK AG",
    "BankAddress": "TAUNUSANLAGE 12, 60254 FRANKFURT AM MAIN, GERMANY",
    "SwiftCode": "DEUTDEFFXXX",
    "AccountName": "ECHO ARYS GMBH",
    "AccountAddress": "MERGENTHALERALLEE 73-75 65760 ESCHBORN, GERMANY",
    "Types": "M1 CASH FUNDS",
    "AuthorizedSignatory": "JAMES PATRICK NORMOYLE",
    "AccountNumber": "DE27500700100920009870",
    "Balance_1": "50,701,959,964,243.00",
    "Balance_2": "74,989,038,856,358.00",
    "Balance_3": "74,989,038,856,358.00",
    "mail": "",
    "reg_date": "2025-01-28 07:55:36",
    "TimeZone": "Europe/Berlin",
    "Note": "Current Account"
  },
  {
    "id": 4,
    "BankName": "BARCLAYS BANK PLC",
    "BankAddress": "1 CHURCHILL PLACE CANARY WHARF, LONDON E14 5HP UK",
    "SwiftCode": "BARCGB22XXX",
    "AccountName": "ECHO ARYS GMBH",
    "AccountAddress": "MERGENTHALERALLEE 73-75 65760 ESCHBORN, GERMANY",
    "Types": "M0",
    "AuthorizedSignatory": "JAMES PATRICK NORMOYLE",
    "AccountNumber": "GB32BARC20325359607800",
    "Balance_1": "₹ 7,49,97,75,47,24,595",
    "Balance_2": "50,000,000.00",
    "Balance_3": "0",
    "mail": "",
    "reg_date": "2025-02-25 16:49:08",
    "TimeZone": "Europe/London",
    "Note": "Current Account"
  },
  {
    "id": 5,
    "BankName": "BARCLAYS BANK PLC",
    "BankAddress": "1 CHURCHILL PLACE, LONDON EC14 5HP",
    "SwiftCode": "BARCGB22",
    "AccountName": "ARTA BUILDING LTD",
    "AccountAddress": "3RD FLOOR 86-90 PAUL STREET LONDON, EC2A 4NE UNITED KINGDOM",
    "Types": "M0",
    "AuthorizedSignatory": "N/A",
    "AccountNumber": "GB11BARC20000052911533",
    "Balance_1": "75,000,786,000,000.00",
    "Balance_2": "",
    "Balance_3": "",
    "mail": "artatld.uk@gmail.com",
    "reg_date": "2024-05-30 15:51:58",
    "TimeZone": "Europe/London",
    "Note": "Current Account"
  },
  {
    "id": 6,
    "BankName": "DEUTSCHE BANK AG",
    "BankAddress": "TAUNUSANLAGE 12, 60254 FRANKFURT AM MAIN, GERMANY",
    "SwiftCode": "DEUTDEFFXXX",
    "AccountName": "ROYAL COAST INVESTMENTS LLC",
    "AccountAddress": "71-75 SHELDON ST. COVENT GARDEN, LONDON WC2H9JQ UNITED KINGDOM",
    "Types": "M0",
    "AuthorizedSignatory": "JUAN NELSON LAINES",
    "AccountNumber": "DE10120700700220052063",
    "Balance_1": "75,000,780,238,800.00",
    "Balance_2": "1,000,000,000.00",
    "Balance_3": "",
    "mail": "pinguinofelice@yahoo.it",
    "reg_date": "2024-09-09 09:50:53",
    "TimeZone": "Asia/Dubai",
    "Note": "Current Account"
  },
  {
    "id": 7,
    "BankName": "DEUTSCHE BANK AG",
    "BankAddress": "TAUNUSANLAGE 12, 60254 FRANKFURT AM MAIN, GERMANY",
    "SwiftCode": "DEUTDEFF",
    "AccountName": "---- VIRTUAL COMPANY -----",
    "AccountAddress": "--- ADDRESS",
    "Types": "M0",
    "AuthorizedSignatory": "N/A",
    "AccountNumber": "DE10120700-------------",
    "Balance_1": "75,000,786,000,000.00",
    "Balance_2": "10,000,000,000.00",
    "Balance_3": "",
    "mail": "pinguinofelice@yahoo.it",
    "reg_date": "2024-05-30 15:52:06",
    "TimeZone": "Europe/Berlin",
    "Note": "Current Account"
  },
  {
    "id": 8,
    "BankName": "DEUTSCHE BANK AG",
    "BankAddress": "TAUNUSANLAGE 12, 60254 FRANKFURT AM MAIN, GERMANY",
    "SwiftCode": "DEUTDEFFXXX",
    "AccountName": "KELLCOR INVESTMENT GMBH",
    "AccountAddress": "MORGARTENSTRASSE 3,  LUZERN, CH-6003,  SWITZERLAND",
    "Types": "M1 Cash Funds",
    "AuthorizedSignatory": "MR. HERBERT KELLER",
    "AccountNumber": "DE43500700100927361600",
    "Balance_1": "23,286,268,219,168.00",
    "Balance_2": "23,000,000,000,000.00",
    "Balance_3": "23,000,000,000,000.00",
    "mail": "pinguinofelice@yahoo.it",
    "reg_date": "2025-02-03 13:24:37",
    "TimeZone": "Europe/Zurich",
    "Note": "Current Account"
  },
  {
    "id": 10,
    "BankName": "DEUTSCHE BANK AG",
    "BankAddress": "DEUTSCHE BANK, 20079 HAMBURG, GERMANY",
    "SwiftCode": "DEUTDEDBHAM",
    "AccountName": "BLACKSHAPE TRADING LTD",
    "AccountAddress": "71-75 SHELTON STREET, COVENT GARDEN, LONDON, WC2H 9JQ, UNITED KINGDOM",
    "Types": "M1",
    "AuthorizedSignatory": "N/A",
    "AccountNumber": "DE79200700240957386633",
    "Balance_1": "9,956,223,004.00",
    "Balance_2": "9,956,223,004.00",
    "Balance_3": "9,956,223,004.00",
    "mail": null,
    "reg_date": "2024-12-03 11:52:10",
    "TimeZone": "Europe/Berlin",
    "Note": "Current Account"
  },
  {
    "id": 11,
    "BankName": "DEUTSCHE BANK AG",
    "BankAddress": "TAUNUSANLAGE 12, 60254 FRANKFURT AM MAIN, GERMANY",
    "SwiftCode": "DEUTDEFF",
    "AccountName": "GIUBI LTD",
    "AccountAddress": "",
    "Types": "M0",
    "AuthorizedSignatory": "N/A",
    "AccountNumber": "DE60500700100361982255",
    "Balance_1": "75,000,782,887,000.00",
    "Balance_2": "60,000,000.00",
    "Balance_3": "0",
    "mail": null,
    "reg_date": "2024-05-30 15:52:18",
    "TimeZone": "Europe/Berlin",
    "Note": "Current Account"
  },
  {
    "id": 12,
    "BankName": "HSBC UK BANK PLC",
    "BankAddress": "8 CANADA SQUARE, CANARY WHARF LONDON, UNITED KINGDOM",
    "SwiftCode": "HBUKGB4BXXX",
    "AccountName": "GLOBAL INFRASTRUCTURE PARTNER",
    "AccountAddress": "UNITED KINGDOM",
    "Types": "M0",
    "AuthorizedSignatory": "RICHARDS THOMAS WILLIAM",
    "AccountNumber": "GB97HBUK40119967366743",
    "Balance_1": "75,000,786,000,000.00",
    "Balance_2": "100,000,000,000.00",
    "Balance_3": "0",
    "mail": "fulljoblimited.uk@gmail.com",
    "reg_date": "2024-06-27 19:47:42",
    "TimeZone": "Europe/London",
    "Note": "Current Account"
  },
  {
    "id": 13,
    "BankName": "UBS SWITZERLAND AG",
    "BankAddress": "BADSTRASSE 12, 5400 BADEN, SWITZERLAND",
    "SwiftCode": "UBSWCHZH80A",
    "AccountName": "BB BIOTECH AG LTD",
    "AccountAddress": "20 ELGIN MEWS, LONDON, ENGLAND, W11 1PU, UK",
    "Types": "M0",
    "AuthorizedSignatory": "SHAWNN BALASUNDRAM SUPPIAH",
    "AccountNumber": "CH900023223211437001M",
    "Balance_1": "74,890,817,875,921",
    "Balance_2": "100,000,000,000.00",
    "Balance_3": "0",
    "mail": "fulljoblimited.uk@gmail.com",
    "reg_date": "2024-10-23 10:23:35",
    "TimeZone": "Europe/Zurich",
    "Note": "Current Account"
  },
  {
    "id": 14,
    "BankName": "DEUTSCHE BANK AG",
    "BankAddress": "TAUNUSANLAGE 12, 60254 FRANKFURT AM MAIN, GERMANY",
    "SwiftCode": "DEUTDEFF",
    "AccountName": "XETRA AG",
    "AccountAddress": "",
    "Types": "M0",
    "AuthorizedSignatory": "N/A",
    "AccountNumber": "005567267",
    "Balance_1": "74,999,707,997,144",
    "Balance_2": "453,467,238,523.65",
    "Balance_3": "4,534,678.23",
    "mail": "pinguinofelice@yahoo.it",
    "reg_date": "2024-05-30 15:52:30",
    "TimeZone": "Europe/Berlin",
    "Note": "Current Account"
  },
  {
    "id": 15,
    "BankName": "COMMERZBANK AG",
    "BankAddress": "KAISERPLATZ 60261, FRANKFURT AM MAIN, GERMANY",
    "SwiftCode": "COBADEFFXXX",
    "AccountName": "MTU AERO ENGINES AG",
    "AccountAddress": "MUNCHEN 80995 GERMANY",
    "Types": "M0",
    "AuthorizedSignatory": "LARS WAGNER",
    "AccountNumber": "DE48700400410220400600",
    "Balance_1": "75,000,785,386,543",
    "Balance_2": "5,000,000,000.00",
    "Balance_3": "",
    "mail": "",
    "reg_date": "2024-06-27 19:45:24",
    "TimeZone": "Europe/Berlin",
    "Note": "Current Account"
  },
  {
    "id": 16,
    "BankName": "CITIBANK N.NA. HONG KONG",
    "BankAddress": "CHAMPION TOWER THREE GARDEN ROAD, CENTRAL, HONG KONG",
    "SwiftCode": "CITIHKHX",
    "AccountName": "FUTHAI OCEAN (HK) LIMITED",
    "AccountAddress": "UNIT NO. A222, 3F, HANG FUNG INDUSTRIAL BUILDING, PHASE 2, NO.2 G HOK YUEN STREET, HUNGHOM, KOWLOON, HONG KONG",
    "Types": "M0",
    "AuthorizedSignatory": "THOMAS SIEGFRIED STEUER",
    "AccountNumber": "705908975",
    "Balance_1": "100,000,000,000.00",
    "Balance_2": "100,000,000,000.00",
    "Balance_3": "0",
    "mail": "pinguinofelice@yahoo.it",
    "reg_date": "2024-05-30 15:52:37",
    "TimeZone": "Asia/Hong_Kong",
    "Note": "Current Account"
  },
  {
    "id": 17,
    "BankName": "DEUTSCHE BANK AG",
    "BankAddress": "TAUNUSANLAGE 12, 60254 FRANKFURT AM MAIN, GERMANY",
    "SwiftCode": "DEUTDEFF",
    "AccountName": "ECHO ARYS GMBH",
    "AccountAddress": "MERGENTHALERALLEE 73-75 65760 ESCHBORN, GERMANY",
    "Types": "M0",
    "AuthorizedSignatory": "JAMES PATRICK NORMOYLE",
    "AccountNumber": "DE76500700100920009861",
    "Balance_1": "47,999,800,000.00",
    "Balance_2": "48,000,000,000.00",
    "Balance_3": "12,237.98",
    "mail": "MAIN ACCOUNT ECHO",
    "reg_date": "2024-05-24 08:44:23",
    "TimeZone": "Europe/Berlin",
    "Note": "Saving Account"
  },
  {
    "id": 18,
    "BankName": "DEUTSCHE BANK AG",
    "BankAddress": "TAUNUSANLAGE 12, 60254 FRANKFURT AM MAIN, GERMANY",
    "SwiftCode": "DEUTDEFF",
    "AccountName": "ROYAL COAST INVESTMENTS LLC",
    "AccountAddress": "71-75 SHELDON ST. COVENT GARDEN, LONDON WC2H9JQ UNITED KINGDOM",
    "Types": "M0",
    "AuthorizedSignatory": "CARLOS A. REMEDI",
    "AccountNumber": "DE43120700700220052051",
    "Balance_1": "799,999,958,370,000",
    "Balance_2": "800,000,000,000.00",
    "Balance_3": "12,237.98",
    "mail": "MAIN ACCOUNT ROYAL COAST INVESTMENT LLC",
    "reg_date": "2024-09-24 06:44:26",
    "TimeZone": "Asia/Dubai",
    "Note": "Saving Account"
  },
  {
    "id": 19,
    "BankName": "DEUTSCHE BANK AG",
    "BankAddress": "TAUNUSANLAGE 12, 60254 FRANKFURT AM MAIN, GERMANY",
    "SwiftCode": "DEUTDEFFXXX",
    "AccountName": "KELLCOR INVESTMENT GMBH",
    "AccountAddress": "MORGARTENSTRASSE 3, LUZERN CH-6003, SWITZERLAND",
    "Types": "M0",
    "AuthorizedSignatory": "HERBERT KELLER",
    "AccountNumber": "DE86500700100927361602",
    "Balance_1": "196,525,085,000",
    "Balance_2": "200,000,000,000.00",
    "Balance_3": "200,000,000,000.00",
    "mail": "pinguinofelice@yahoo.it",
    "reg_date": "2024-12-24 17:39:48",
    "TimeZone": "Europe/Berlin",
    "Note": "Saving Account"
  },
  {
    "id": 21,
    "BankName": "BARCLAYS BANK PLC",
    "BankAddress": "LEICESTER LE87 2BB UNITED KINGDOM (GB)",
    "SwiftCode": "BARCGB22XXX",
    "AccountName": "SURIA GLOBAL (L) LTD",
    "AccountAddress": "UNIT LEVEL 11(A), MAIN OFFICE TOWER, FINANCIAL PARK LABUAN, JALAN MERDEKA, WILAYAH, PERSEKUTUAN LABUAN, 87000 MALAYSIA",
    "Types": "M1",
    "AuthorizedSignatory": "OMAR YASSIN BIN ABDULLAH",
    "AccountNumber": "GB62BARC20473599777526",
    "Balance_1": "64,894,578,934,189,200,000,000.00",
    "Balance_2": "57,895,478,923,248,223,789,272,389.00",
    "Balance_3": "56.890.458.204.112.552.341.251,91",
    "mail": "pinguinofelice@yahoo.it",
    "reg_date": "2024-11-29 18:15:24",
    "TimeZone": "Europe/London",
    "Note": "Current Account"
  },
  {
    "id": 22,
    "BankName": "DEUTSCHE BANK AG",
    "BankAddress": "TAUNUSANLAGE 12, 60254 FRANKFURT AM MAIN, GERMANY",
    "SwiftCode": "DEUTDEFFXXX",
    "AccountName": "EMAGOLD TURIZM VE DIS TIC. SAN. A.S.",
    "AccountAddress": "ORHANGAZI MAH. BEYZADE SOK N.8/A SULTANBEYLI, TURKEY",
    "Types": "M0",
    "AuthorizedSignatory": "MEHMET AKGUL",
    "AccountNumber": "DE47500700100085696311",
    "Balance_1": "70,000,000,000,000.00",
    "Balance_2": "100,000,000,000.00",
    "Balance_3": "100,000,000,000.00",
    "mail": "pinguinofelice@yahoo.it",
    "reg_date": "2024-12-02 11:14:12",
    "TimeZone": "Europe/Berlin",
    "Note": "Current Account"
  },
  {
    "id": 23,
    "BankName": "BARCLAYS BANK PLC",
    "BankAddress": "LEICESTER LE87 2BB, UNITED KINGDOM",
    "SwiftCode": "BARCGB22XXX",
    "AccountName": "EMAGOLD TURIZM VE DIS TIC. SAN. A.S.",
    "AccountAddress": "ORHANGAZI MAH. BEYZADE SOK N.8/A SULTANBEYLI, TURKEY",
    "Types": "M0",
    "AuthorizedSignatory": "MEHMET AKGUL",
    "AccountNumber": "GB12BARC20325369609733",
    "Balance_1": "70,000,000,000,000.00",
    "Balance_2": "100,000,000,000.00",
    "Balance_3": "100,000,000,000.00",
    "mail": "pinguinofelice@yahoo.it",
    "reg_date": "2024-12-02 11:14:19",
    "TimeZone": "Europe/London",
    "Note": "Current Account"
  },
  {
    "id": 24,
    "BankName": "BARCLAYS BANK PLC",
    "BankAddress": "LEICESTER LE87 2BB, UNITED KINGDOM",
    "SwiftCode": "BARCGB22XXX",
    "AccountName": "FUTHAI OCEAN (HK) LIMITED",
    "AccountAddress": "UNIT NO. A222, 3F, HANG FUNG INDUSTRIAL BUILDING, PHASE 2, NO.2 G HOK YUEN STREET, HUNGHOM, KOWLOON, HONG KONG",
    "Types": "M0",
    "AuthorizedSignatory": "FANG WONG",
    "AccountNumber": "GB34BARC20325369609822",
    "Balance_1": "99,995,009,200.00",
    "Balance_2": "100,000,000,000.00",
    "Balance_3": "100,000,000,000.00",
    "mail": "pinguinofelice@yahoo.it",
    "reg_date": "2024-05-30 16:07:33",
    "TimeZone": "Europe/London",
    "Note": "Current Account"
  },
  {
    "id": 25,
    "BankName": "DEUTSCHE BANK AG",
    "BankAddress": "TAUNUSANLAGE 12, 60254 FRANKFURT AM MAIN, GERMANY",
    "SwiftCode": "DEUTDEFFXXX",
    "AccountName": "FUTHAI OCEAN (HK) LIMITED",
    "AccountAddress": "UNIT NO. A222, 3F, HANG FUNG INDUSTRIAL BUILDING, PHASE 2, NO.2 G HOK YUEN STREET, HUNGHOM, KOWLOON, HONG KONG",
    "Types": "M0",
    "AuthorizedSignatory": "JOSHUA DEAN ROBERT RAPANA",
    "AccountNumber": "DE42500700100085696304",
    "Balance_1": "99,629,459,000.00",
    "Balance_2": "100,000,000,000.00",
    "Balance_3": "100,000,000,000.00",
    "mail": "pinguinofelice@yahoo.it",
    "reg_date": "2024-12-11 06:59:28",
    "TimeZone": "Europe/Berlin",
    "Note": "Current Account"
  },
  {
    "id": 26,
    "BankName": "BARCLAYS BANK PLC",
    "BankAddress": "LEICESTER LE87 2BB,UNITED KINGDOM",
    "SwiftCode": "BARCGB22",
    "AccountName": "ALLIANCE GLOBAL BANCO LTD",
    "AccountAddress": "THE BRISTOL OFFICE, 2ND FLOOR 5 HIGH STREET, WESTBURY ON TRYM, BRISTOL, ENGLAND, BS9 3BY",
    "Types": "M0",
    "AuthorizedSignatory": "MICHAEL GEBREKIDANE GEBREHIWET",
    "AccountNumber": "GB89BARC20325357226200",
    "Balance_1": "150,000,000.00",
    "Balance_2": "150,000,000.00",
    "Balance_3": "0",
    "mail": "pinguinofelice@gmail.com",
    "reg_date": "2024-05-30 15:53:47",
    "TimeZone": "Europe/London",
    "Note": "Current Account"
  },
  {
    "id": 27,
    "BankName": "DEUTSCHE BANK AG",
    "BankAddress": "TAUNUSANLAGE 12, 60254, FRANKFURT AM MAIN, GERMANY",
    "SwiftCode": "DEUTDEFFXXX",
    "AccountName": "POINT PIER LIMITED",
    "AccountAddress": "PO BOX PE11SA, RAFI MALIK ECO INNOVATION CENTRE, ST. PETERS COURT, CITY ROAD, PETERBOROUGH, UNITED KINGDOM, PE1 1SA",
    "Types": "M0",
    "AuthorizedSignatory": "AKRAM AHMED SHEIKH",
    "AccountNumber": "DE26500700100957199300",
    "Balance_1": "299,288,652,524,169",
    "Balance_2": "30,000,000,000,000.00",
    "Balance_3": "0",
    "mail": "pinguinofelice@gmail.com",
    "reg_date": "2024-06-14 09:07:37",
    "TimeZone": "Europe/Berlin",
    "Note": "Current Account"
  },
  {
    "id": 28,
    "BankName": "UNITED OVERSEAS BANK LIMITED",
    "BankAddress": "80 RAFFLES PLACE UOB PLAZA SINGAPORE, 048624 SINGAPORE",
    "SwiftCode": "UOVBSGSG",
    "AccountName": "SURIA GLOBAL (S) PTE LTD",
    "AccountAddress": "112 ROBINSON ROAD #05-01 ROBINSON 112 SINGAPORE (068902)",
    "Types": "M0",
    "AuthorizedSignatory": "OMAR YASSIN BIN ABDULLAH",
    "AccountNumber": "9102039711",
    "Balance_1": "57,447,893,473,489.23",
    "Balance_2": "57,447,893,473,489.23",
    "Balance_3": "0",
    "mail": "pinguinofelice@yahoo.it",
    "reg_date": "2024-05-30 15:53:50",
    "TimeZone": "Asia/Singapore",
    "Note": "Current Account"
  },
  {
    "id": 29,
    "BankName": "BARCLAYS BANK PLC",
    "BankAddress": "1 CHURCHILL PLACE LONDON UK E14 5HP",
    "SwiftCode": "BUKBGB22",
    "AccountName": "POINT PIER LIMITED",
    "AccountAddress": "PO BOX PE11SA, RAFI MALIK ECO INNOVATION CENTRE, ST. PETERS COURT, CITY ROAD, PETERBOROUGH, UNITED KINGDOM, PE1 1SA",
    "Types": "M0",
    "AuthorizedSignatory": "SHEIKH MUFASSIR AHMED",
    "AccountNumber": "GB26BARC20003460830887",
    "Balance_1": "4,975,250,000",
    "Balance_2": "5,000,000,000.00",
    "Balance_3": "0",
    "mail": "jackyusa@protonmail.com ",
    "reg_date": "2024-06-14 09:07:37",
    "TimeZone": "Europe/London",
    "Note": "Current Account"
  },
  {
    "id": 30,
    "BankName": "DEUTSCHE BANK AG",
    "BankAddress": "TAUNUSANLAGE 12, 60254 FRANKFURT AM MAIN, GERMANY",
    "SwiftCode": "DEUTDEFFXXX",
    "AccountName": "SUNSHINE INT`L GROUP CO., LIMITED",
    "AccountAddress": "FLAT 8, BLK A, 5/F, TAK LEE INDUSTRIAL CENTRE, 8 TSING YEUNG CIRCUIT, NT, HONG KONG",
    "Types": "M0",
    "AuthorizedSignatory": "YIP KIN",
    "AccountNumber": "DE84500700100955722401",
    "Balance_1": "975,632,737,500.00",
    "Balance_2": "978,000,000,000.00",
    "Balance_3": "0.0",
    "mail": "pinguinofelice@yahoo.it",
    "reg_date": "2024-05-30 15:53:54",
    "TimeZone": "Europe/Berlin",
    "Note": "Current Account"
  },
  {
    "id": 31,
    "BankName": "BARCLAYS BANK PLC",
    "BankAddress": "1 CHURCHILL PLACE CANARY WHARF, LONDON E14 5HP UK",
    "SwiftCode": "BARCGB22XXX",
    "AccountName": "SUNSHINE INT`L GROUP CO., LIMITED",
    "AccountAddress": "FLAT 8, BLK A, 5/F, TAK LEE INDUSTRIAL CENTRE, 8 TSING YEUNG CIRCUIT, NT, HONG KONG",
    "Types": "M0",
    "AuthorizedSignatory": "YIP KIN",
    "AccountNumber": "GB10BUKB20679063061599",
    "Balance_1": "12,800,000,000,000.00",
    "Balance_2": "12,800,000,000,000.00",
    "Balance_3": "0.0",
    "mail": "pinguinofelice@yahoo.it",
    "reg_date": "2024-05-30 15:53:55",
    "TimeZone": "Europe/London",
    "Note": "Current Account"
  },
  {
    "id": 32,
    "BankName": "DEUTSCHE BANK AG",
    "BankAddress": "TAUNUSANLAGE 12, 60254 FRANKFURT AM MAIN, GERMANY",
    "SwiftCode": "DEUTDEFFXXX",
    "AccountName": "SURIA GLOBAL (L) LIMITED",
    "AccountAddress": "",
    "Types": "M0",
    "AuthorizedSignatory": "OMAR YASSIN BIN ABDULLAH",
    "AccountNumber": "DE72500700100064329671",
    "Balance_1": "12,383,221,208,171.30",
    "Balance_2": "50,000,000,000.00",
    "Balance_3": "0.00",
    "mail": "daniele.tasciotti@gmail.com",
    "reg_date": "2024-12-02 10:11:06",
    "TimeZone": "Europe/Berlin",
    "Note": "Current Account"
  },
  {
    "id": 33,
    "BankName": "DEUTSCHE BANK AG",
    "BankAddress": "TAUNUSANLAGE 12, 60254 FRANKFURT AM MAIN, GERMANY",
    "SwiftCode": "DEUTDEFFXXX",
    "AccountName": "FUTHAI OCEAN (HK) LIMITED",
    "AccountAddress": "UNIT NO. A222, 3F, HANG FUNG INDUSTRIAL BUILDING, PHASE 2, NO.2 G HOK YUEN STREET, HUNGHOM, KOWLOON, HONG KONG",
    "Types": "M0",
    "AuthorizedSignatory": "THOMAS SIEGFRIED STEUER",
    "AccountNumber": "DE25500700100082647997",
    "Balance_1": "26,198,269,185",
    "Balance_2": "50,000,000,000.00",
    "Balance_3": "0.00",
    "mail": "daniele.tasciotti@gmail.com",
    "reg_date": "2024-05-30 15:57:42",
    "TimeZone": "Europe/Berlin",
    "Note": "Saving Account"
  },
  {
    "id": 34,
    "BankName": "DEUTSCHE BANK AG",
    "BankAddress": "TAUNUSANLAGE 12, 60254 FRANKFURT AM MAIN, GERMANY",
    "SwiftCode": "DEUTDEFFXXX",
    "AccountName": "AURUBIS AG",
    "AccountAddress": "Aurubis AG Hovestrasse 50 20539 Hamburg",
    "Types": "M0",
    "AuthorizedSignatory": "Roland Harings",
    "AccountNumber": "DE91500700100927361609",
    "Balance_1": "5,214,390,864.78",
    "Balance_2": "10,000,000,000.00",
    "Balance_3": "10,000,000,000.00",
    "mail": "pinguinofelice@gmail.com",
    "reg_date": "2024-05-30 15:54:01",
    "TimeZone": "Europe/Berlin",
    "Note": "Current Account"
  },
  {
    "id": 35,
    "BankName": "HSBC BANK PLC",
    "BankAddress": "1 CENTENARY SQUARE,BIRMINGHAM,B1 1HQ UK",
    "SwiftCode": "MIDLGB22",
    "AccountName": "SURIA GLOBAL (L) LTD",
    "AccountAddress": "UNIT LEVEL 11(A), MAIN OFFICE TOWER, FINANCIAL PARK LABUAN,JALAN MERDEKA, WILAYAH,PERSEKUTUAN LABUAN, 87000 MALAYSIA",
    "Types": "M0",
    "AuthorizedSignatory": "OMAR YASSIN BIN ABDULLAH",
    "AccountNumber": "GB64HBUK40119984501999",
    "Balance_1": "65,465,445,895.40",
    "Balance_2": "65,465,445,895.40",
    "Balance_3": "65,465,445,895.40",
    "mail": "pinguinofelice@yahoo.it",
    "reg_date": "2024-05-30 15:54:03",
    "TimeZone": "Europe/London",
    "Note": "Current Account"
  },
  {
    "id": 36,
    "BankName": "BARCLAYS BANK PLC",
    "BankAddress": "LEICESTER LE87 2BB UNITED KINGDOM (GB)",
    "SwiftCode": "BARCGB22",
    "AccountName": "SURIA GLOBAL (L) LTD",
    "AccountAddress": "UNIT LEVEL 11(A), MAIN OFFICE TOWER, FINANCIAL PARK LABUAN,JALAN MERDEKA, WILAYAH,PERSEKUTUAN LABUAN, 87000 MALAYSIA",
    "Types": "M0",
    "AuthorizedSignatory": "OMAR YASSIN BIN ABDULLAH",
    "AccountNumber": "GB30BARC20325357226777",
    "Balance_1": "7,999,340,000.00",
    "Balance_2": "6,250,000,000.00",
    "Balance_3": "474.389.467.823,91",
    "mail": "pinguinofelice@yahoo.it",
    "reg_date": "2024-05-30 15:54:05",
    "TimeZone": "Europe/London",
    "Note": "Current Account"
  },
  {
    "id": 37,
    "BankName": "DEUTSCHE BANK AG",
    "BankAddress": "TAUNUSANLAGE 12, 60254 FRANKFURT AM MAIN, GERMANY",
    "SwiftCode": "DEUTDEFFXXX",
    "AccountName": "FRANKLIN AND FIDELITY INVESTMENT (H.K.) LIMITED",
    "AccountAddress": "RM.517,NEW CITY CENTRE,2 LEI YUE MUN ROAD,KWUN TONG, KOWLOON HONG KONG",
    "Types": "M0",
    "AuthorizedSignatory": "SHYAM LAL THAKUR ",
    "AccountNumber": "DE21500700100361982267",
    "Balance_1": "29,999,429,399,900.00",
    "Balance_2": "30,000,000,000,000.00",
    "Balance_3": "30,000,000,000,000.00",
    "mail": "pinguinofelice@yahoo.it",
    "reg_date": "2024-12-11 06:53:55",
    "TimeZone": "Europe/Berlin",
    "Note": "Current Account"
  },
  {
    "id": 38,
    "BankName": "BARCLAYS BANK PLC",
    "BankAddress": "LEICESTER LE87 2BB UNITED KINGDOM",
    "SwiftCode": "BARCGB22",
    "AccountName": "CINTECH (HONG KONG) LIMITED",
    "AccountAddress": "13/F WAH KIT COMM. CENTER,300 DES VOUEX RD CENTRAL HONG KONG",
    "Types": "M0",
    "AuthorizedSignatory": "SHYAM LAL THAKUR",
    "AccountNumber": "GB97BARC20325348607800",
    "Balance_1": "35,000,000,000,000.00",
    "Balance_2": "35,000,000,000,000.00",
    "Balance_3": "0",
    "mail": "pinguinofelice@yahoo.it",
    "reg_date": "2024-05-30 15:54:18",
    "TimeZone": "Europe/London",
    "Note": "Current Account"
  },
  {
    "id": 39,
    "BankName": "DEUTSCHE BANK AG",
    "BankAddress": "TAUNUSANLAGE 12, 60254 FRANKFURT AM MAIN, GERMANY",
    "SwiftCode": "DEUTDEFFXXX",
    "AccountName": "MICROGOLD INVESTMENT GROUP FLLC",
    "AccountAddress": "MIRZO ULUG BEK DISTRICT, PARKENT-2 STREET, 3-114 TASHKENT UZBEKISTAN",
    "Types": "CASH",
    "AuthorizedSignatory": "HASSAN ASGHARZADEH",
    "AccountNumber": "DE98500700100361982239",
    "Balance_1": "1,000,000,000,000.00",
    "Balance_2": "1,000,000,000,000.00",
    "Balance_3": "1,000,000,000,000.00",
    "mail": "",
    "reg_date": "2024-05-30 15:54:23",
    "TimeZone": "Europe/Berlin",
    "Note": "Current Account"
  },
  {
    "id": 41,
    "BankName": "DEUTSCHE BANK AG",
    "BankAddress": "TAUNUSANLAGE 12, 60254 FRANKFURT AM MAIN, GERMANY",
    "SwiftCode": "DEUTDEFFXXX",
    "AccountName": "HYDRA GLOBAL HOLDINGS PTE. LTD",
    "AccountAddress": "31 FERNVALE ROAD NO. 14-44 HIGH PARK RESIDENCES, SINGAPORE, 797417",
    "Types": "M0",
    "AuthorizedSignatory": "ADIL IDREES MALIK",
    "AccountNumber": "DE79500700100361982290",
    "Balance_1": "10,000,000,000,000.00",
    "Balance_2": "10,000,000,000,000.00",
    "Balance_3": "10,000,000,000,000.00",
    "mail": "N/A",
    "reg_date": "2024-05-23 09:42:42",
    "TimeZone": "Europe/Berlin",
    "Note": "Current Account"
  },
  {
    "id": 42,
    "BankName": "DEUTSCHE BANK AG",
    "BankAddress": "TAUNUSANLAGE 12, 60254 FRANKFURT AM MAIN, GERMANY",
    "SwiftCode": "DEUTDEFFXXX",
    "AccountName": "FIRST SWISS DEPOSITORY LTD",
    "AccountAddress": "71-75, SHELTON STREET WC2H 9JQ LONDON, UNITED KINGDOM",
    "Types": "M0",
    "AuthorizedSignatory": "ANTHONY RAYMOND WHEAR",
    "AccountNumber": "DE56500700100361989785",
    "Balance_1": "99,950,000,000",
    "Balance_2": "100,000,000,000.00",
    "Balance_3": "0",
    "mail": "pinguinofelice@yahoo.it",
    "reg_date": "2024-05-30 15:54:28",
    "TimeZone": "Europe/Berlin",
    "Note": "Current Account"
  },
  {
    "id": 43,
    "BankName": "DEUTSCHE BANK AG",
    "BankAddress": "TAUNUSANLAGE 12, 60254 FRANKFURT AM MAIN, GERMANY",
    "SwiftCode": "DEUTDEFFXXX",
    "AccountName": "LIFETIME RESERVE INC.",
    "AccountAddress": "2651 JOHE STREET SUITE 1,MARKHAM, ONTARIO, CANADA L3R 2W5",
    "Types": "M0",
    "AuthorizedSignatory": "HUA YANG",
    "AccountNumber": "DE35500700100361982209",
    "Balance_1": "500,000,000,000,000",
    "Balance_2": "505,000,000,000,000.00",
    "Balance_3": "10,000,000,000,000.00",
    "mail": "pinguinofelice@yahoo.it",
    "reg_date": "2025-01-10 15:29:46",
    "TimeZone": "Europe/Berlin",
    "Note": "Current Account"
  },
  {
    "id": 44,
    "BankName": "DEUTSCHE BANK AG",
    "BankAddress": "TAUNUSANLAGE 12, 60254 FRANKFURT AM MAIN, GERMANY",
    "SwiftCode": "DEUTDEFFXXX",
    "AccountName": "HYDRA GLOBAL HOLDINGS PTE. LTD",
    "AccountAddress": "31 FERNVALE ROAD NO. 14-44 HIGH PARK RESIDENCES, SINGAPORE, 797417",
    "Types": "M0",
    "AuthorizedSignatory": "ADIL IDREES MALIK",
    "AccountNumber": "DE30500700100361982202",
    "Balance_1": "499,999,930,544,169.00",
    "Balance_2": "499,999,930,544,169.00",
    "Balance_3": "499,999,930,544,169.00",
    "mail": "N/A",
    "reg_date": "2024-05-23 09:40:35",
    "TimeZone": "Europe/Berlin",
    "Note": "Saving Account"
  },
  {
    "id": 45,
    "BankName": "DEUTSCHE BANK AG",
    "BankAddress": "TAUNUSANLAGE 12, 60254, FRANKFURT AM MAIN, GERMANY",
    "SwiftCode": "DEUTDEFFXXX",
    "AccountName": "STABLE TOWER LIMITED",
    "AccountAddress": "ECO INNOVATION CENTRE ST.PETERS COURT, PETERBOROUGH, UNITED KINGDOM , PE1 1SA",
    "Types": "M0",
    "AuthorizedSignatory": "AKRAM AHMED SHEIKH",
    "AccountNumber": "DE91500700100361963256",
    "Balance_1": "100,000,000,000,000.00",
    "Balance_2": "100,000,000,000,000.00",
    "Balance_3": "100,000,000,000,000.00",
    "mail": "",
    "reg_date": "2024-06-08 15:03:17",
    "TimeZone": "Europe/Berlin",
    "Note": "Current Account"
  },
  {
    "id": 46,
    "BankName": "BARCLAYS BANK PLC",
    "BankAddress": "LEICESTER LE87 2BB UNITED KINGDOM",
    "SwiftCode": "BARCGB22XXX",
    "AccountName": "SURIA GLOBAL (L) LTD",
    "AccountAddress": "48 WARWICK STREET , LONDON , ENGLAND , W1B 5AW, UNITED KINGDOM",
    "Types": "M0",
    "AuthorizedSignatory": "OMAR YASSIN BIN ABDULLAH",
    "AccountNumber": "GB74BARC20473543156664",
    "Balance_1": "583,337,255.89",
    "Balance_2": "170,780,208,416.28",
    "Balance_3": "TOP SECRET",
    "mail": "",
    "reg_date": "2024-06-14 22:27:14",
    "TimeZone": "Europe/London",
    "Note": "CURRENT ACCOUNT"
  },
  {
    "id": 47,
    "BankName": "DEUTSCHE BANK AG",
    "BankAddress": "TAUNUSANLAGE 12, 60254, FRANKFURT AM MAIN, GERMANY",
    "SwiftCode": "DEUTDEFFXXX",
    "AccountName": "PRAISE SKY (HONG KONG) LIMITED",
    "AccountAddress": "UNIT 1202, 12/F, ORIENTAL CENTER, 67-71 CHATHAM ROAD, TST, HONG KONG",
    "Types": "M0",
    "AuthorizedSignatory": "YIP KIN",
    "AccountNumber": "DE7850070010090009825",
    "Balance_1": "1,000,000,000,000.00",
    "Balance_2": "1,000,000,000,000.00",
    "Balance_3": "1,000,000,000,000.00",
    "mail": "NA",
    "reg_date": "2024-07-05 16:44:48",
    "TimeZone": "Europe/Berlin",
    "Note": "CURRENT ACCOUNT"
  },
  {
    "id": 48,
    "BankName": "DEUTSCHE BANK AG",
    "BankAddress": "TAUNUSANLAGE 12, 60254, FRANKFURT AM MAIN, GERMANY",
    "SwiftCode": "DEUTDEFFXXX",
    "AccountName": "ADAPTIS GMBH",
    "AccountAddress": "SONNMATTSTRASSE 12, 4142, MUNCHENSTEIN, SWITZERLAND",
    "Types": "M1 CASH FUNDS",
    "AuthorizedSignatory": "ADAM JAMES EASTBURN",
    "AccountNumber": "DE69500700100361982276",
    "Balance_1": "30,000,000,000,000.00",
    "Balance_2": "30,000,000,000,000.00",
    "Balance_3": "30,000,000,000,000.00",
    "mail": "N/A",
    "reg_date": "2025-01-30 12:15:44",
    "TimeZone": "Europe/Berlin",
    "Note": "CURRENT ACCOUNT"
  },
  {
    "id": 49,
    "BankName": "DEUTSCHE BANK AG",
    "BankAddress": "TAUNUSANLAGE 12, 60254, FRANKFURT AM MAIN, GERMANY",
    "SwiftCode": "DEUTDEFFXXX",
    "AccountName": "POINT PIER UK LIMITED",
    "AccountAddress": "ECO INNOVATION CENTRE ST. PETERS COURT, CITY ROAD, PETERBOROUGH, UNITED KINGDOM, PE1 1SA",
    "Types": "M0",
    "AuthorizedSignatory": "AKRAM AHMED SHEIKH",
    "AccountNumber": "DE61500700100953110411",
    "Balance_1": "1,000,000,000,000,000.00",
    "Balance_2": "1,000,000,000,000,000.00",
    "Balance_3": "1,000,000,000,000,000.00",
    "mail": "",
    "reg_date": "2024-12-03 11:47:16",
    "TimeZone": "Europe/Berlin",
    "Note": "CURRENT ACCOUNT"
  },
  {
    "id": 50,
    "BankName": "DEUTSCHE BANK AG",
    "BankAddress": "WINCHESTER HOUSE 23, GREAT WINCHESTER STREET, LONDON, EC2P 2AX, UNITED KINGDOM",
    "SwiftCode": "DEUTGB22XXX",
    "AccountName": "POINT PIER UK LIMITED",
    "AccountAddress": "ECO INNOVATION CENTRE ST. PETERS COURT, CITY ROAD, PETERBOROUGH, UNITED KINGDOM, PE1 1SA",
    "Types": "M0",
    "AuthorizedSignatory": "AKRAM AHMED SHEIKH",
    "AccountNumber": "GB94DEUT23104819268299",
    "Balance_1": "500,000,000,000,000.00",
    "Balance_2": "500,000,000,000,000.00",
    "Balance_3": "500,000,000,000,000.00",
    "mail": "",
    "reg_date": "2024-07-20 18:59:26",
    "TimeZone": "Europe/London",
    "Note": "CURRENT ACCOUNT"
  },
  {
    "id": 51,
    "BankName": "DEUTSCHE BANK AG",
    "BankAddress": "TAUNUSANLAGE 12, 60254, FRANKFURT AM MAIN, GERMANY",
    "SwiftCode": "DEUTDEFFXXX",
    "AccountName": "AEGEA GERMANY GMBH",
    "AccountAddress": "BOCKENHEIMER LANDSTRASSE 17-19 FRANKFURT AM MAIN,GERMANY",
    "Types": "M1",
    "AuthorizedSignatory": "ING. JAROSLAV BLAHA",
    "AccountNumber": "DE55500700100039487404",
    "Balance_1": "7,528,100,645.00",
    "Balance_2": "7,528,100,645.00",
    "Balance_3": "7,528,100,645.00",
    "mail": "",
    "reg_date": "2024-12-08 12:44:39",
    "TimeZone": "Europe/Berlin",
    "Note": "CURRENT ACCOUNT"
  },
  {
    "id": 52,
    "BankName": "DEUTSCHE BANK AG",
    "BankAddress": "TAUNUSANLAGE 12, 60254, FRANKFURT AM MAIN, GERMANY",
    "SwiftCode": "DEUTDEFFXXX",
    "AccountName": "AVANTULO S.A.",
    "AccountAddress": "SOHO CENTRE CALLE 50, AVANTULO TOWERS I II III, PANAMA CITY, N/A, N/A, PANAMA",
    "Types": "M1",
    "AuthorizedSignatory": "MR. FRANCIS ANTHONY JANKAUSKAS",
    "AccountNumber": "DE60500700100361982244",
    "Balance_1": "25,000,000,000,000.00",
    "Balance_2": "25,000,000,000,000.00",
    "Balance_3": "25,000,000,000,000.00",
    "mail": "",
    "reg_date": "2025-02-03 07:55:58",
    "TimeZone": "Europe/Berlin",
    "Note": "CURRENT ACCOUNT"
  },
  {
    "id": 57,
    "BankName": "DEUTSCHE BANK AG",
    "BankAddress": "TAUNUSANLAGE 12, 60254, FRANKFURT AM MAIN, GERMANY",
    "SwiftCode": "DEUTDEFFXXX",
    "AccountName": "SURIA GLOBAL (L) LIMITED",
    "AccountAddress": "NO. 8 ",
    "Types": "",
    "AuthorizedSignatory": "MR. OMAR YASSIN BIN ABDULLAH",
    "AccountNumber": "DE72500700100064329671",
    "Balance_1": "",
    "Balance_2": "",
    "Balance_3": "",
    "mail": "",
    "reg_date": "2025-01-28 16:34:34",
    "TimeZone": "Europe/Berlin",
    "Note": ""
  },
  {
    "id": 58,
    "BankName": "DEUTSCHE BANK AG",
    "BankAddress": "TAUNUSANLAGE 12, 60254, FRANKFURT AM MAIN, GERMANY",
    "SwiftCode": "DEUTDEFFXXX",
    "AccountName": "Company Name",
    "AccountAddress": "Company Address",
    "Types": "M1",
    "AuthorizedSignatory": "Mr. John Doe",
    "AccountNumber": "IBAN or AccountNumber",
    "Balance_1": "1,000,000,000.00",
    "Balance_2": "1,000,000,000.00",
    "Balance_3": "1,000,000,000.00",
    "mail": "",
    "reg_date": "2025-02-06 07:23:36",
    "TimeZone": "Europe/Berlin",
    "Note": "CURRENT ACCOUNT"
  },
  {
    "id": 59,
    "BankName": "DEUTSCHE BANK AG",
    "BankAddress": "TAUNUSANLAGE 12, 60254, FRANKFURT AM MAIN, GERMANY",
    "SwiftCode": "DEUTDEFFXXX",
    "AccountName": "YASSINE BOUYAFA",
    "AccountAddress": "BERNADETTELAAN 13, 2212 AC NOORDWIJKERHOUT, THE NETHERLANDS",
    "Types": "M1",
    "AuthorizedSignatory": "MR. YASSINE BOUYAFA",
    "AccountNumber": "DE50500700100613341725",
    "Balance_1": "800,000,000.00",
    "Balance_2": "800,000,000.00",
    "Balance_3": "800,000,000.00",
    "mail": "",
    "reg_date": "2025-02-06 07:32:27",
    "TimeZone": "Europe/Berlin",
    "Note": "CURRENT ACCOUNT"
  },
  {
    "id": 60,
    "BankName": "DEUTSCHE BANK AG",
    "BankAddress": "KAISTERSTRASSE 90, D-76133 KARLSRUHE, GERMANY",
    "SwiftCode": "DEUTDEDB660",
    "AccountName": "BILDERBERG INVESTMENT GROUP CO. LTD",
    "AccountAddress": "A.D. VOGELHARDT 8, D-76149, GERMANY",
    "Types": "M1",
    "AuthorizedSignatory": "MR. AHNAKOT DENIS GIGIL",
    "AccountNumber": "DE51660700240097750400",
    "Balance_1": "50,000,000,000.00",
    "Balance_2": "50,000,000,000.00",
    "Balance_3": "50,000,000,000.00",
    "mail": "",
    "reg_date": "2025-02-10 18:14:24",
    "TimeZone": "Europe/Berlin",
    "Note": "CURRENT ACCOUNT"
  }
]